techui_builder/__init__.py
techui_builder/__main__.py
techui_builder/_version.py
techui_builder/autofill.py
techui_builder/builder.py
techui_builder/generate.py
techui_builder/models.py
techui_builder/schema_generator.py
techui_builder/utils.py
techui_builder/validator.py
techui_builder-0.5.2a3.dist-info/licenses/LICENSE
techui_builder-0.5.2a3.dist-info/METADATA
techui_builder-0.5.2a3.dist-info/WHEEL
techui_builder-0.5.2a3.dist-info/entry_points.txt
techui_builder-0.5.2a3.dist-info/top_level.txt
techui_builder-0.5.2a3.dist-info/RECORD
