Metadata-Version: 2.4
Name: techui-builder
Version: 0.5.2a3
Summary: A package for building Phoebus GUIs
Author-email: Oliver Copping <oliver.copping@diamond.ac.uk>, Adedamola Sode <adedamola.sode@diamond.ac.uk>, Niamh Dougan <niamh.dougan@diamond.ac.uk>
Project-URL: GitHub, https://github.com/DiamondLightSource/techui-builder
Classifier: Development Status :: 3 - Alpha
Classifier: Programming Language :: Python :: 3.12
Classifier: Programming Language :: Python :: 3.13
Requires-Python: <4.0,>=3.12
License-File: LICENSE
Requires-Dist: pyyaml>=6.0.2
Requires-Dist: phoebusgen>=3.0.0
Requires-Dist: lxml>=5.4.0
Requires-Dist: typer>=0.16.0
Requires-Dist: rich>=14.1.0
Requires-Dist: pydantic>=2.11.7
Dynamic: license-file
